kbki_classifier/__init__.py
kbki_classifier/app.py
kbki_classifier/classifier.py
kbki_classifier/downloader.py
kbki_classifier_deplearning_s-0.1.7.dist-info/licenses/LICENSE
kbki_classifier_deplearning_s-0.1.7.dist-info/METADATA
kbki_classifier_deplearning_s-0.1.7.dist-info/WHEEL
kbki_classifier_deplearning_s-0.1.7.dist-info/entry_points.txt
kbki_classifier_deplearning_s-0.1.7.dist-info/top_level.txt
kbki_classifier_deplearning_s-0.1.7.dist-info/RECORD
